__init__.py
aioqui/__init__.py
aioqui/asynq.py
aioqui/.assets/icons/activity.svg
aioqui/.assets/icons/airplay.svg
aioqui/.assets/icons/alert-circle.svg
aioqui/.assets/icons/alert-octagon.svg
aioqui/.assets/icons/alert-triangle.svg
aioqui/.assets/icons/align-center.svg
aioqui/.assets/icons/align-justify.svg
aioqui/.assets/icons/align-left.svg
aioqui/.assets/icons/align-right.svg
aioqui/.assets/icons/anchor.svg
aioqui/.assets/icons/aperture.svg
aioqui/.assets/icons/archive.svg
aioqui/.assets/icons/arrow-down-circle.svg
aioqui/.assets/icons/arrow-down-left.svg
aioqui/.assets/icons/arrow-down-right.svg
aioqui/.assets/icons/arrow-down.svg
aioqui/.assets/icons/arrow-left-circle.svg
aioqui/.assets/icons/arrow-left.svg
aioqui/.assets/icons/arrow-right-circle.svg
aioqui/.assets/icons/arrow-right.svg
aioqui/.assets/icons/arrow-up-circle.svg
aioqui/.assets/icons/arrow-up-left.svg
aioqui/.assets/icons/arrow-up-right.svg
aioqui/.assets/icons/arrow-up.svg
aioqui/.assets/icons/at-sign.svg
aioqui/.assets/icons/award.svg
aioqui/.assets/icons/bar-chart-2.svg
aioqui/.assets/icons/bar-chart.svg
aioqui/.assets/icons/battery-charging.svg
aioqui/.assets/icons/battery.svg
aioqui/.assets/icons/bell-off.svg
aioqui/.assets/icons/bell.svg
aioqui/.assets/icons/bluetooth.svg
aioqui/.assets/icons/bold.svg
aioqui/.assets/icons/book-open.svg
aioqui/.assets/icons/book.svg
aioqui/.assets/icons/bookmark.svg
aioqui/.assets/icons/box.svg
aioqui/.assets/icons/briefcase.svg
aioqui/.assets/icons/calendar.svg
aioqui/.assets/icons/camera-off.svg
aioqui/.assets/icons/camera.svg
aioqui/.assets/icons/cast.svg
aioqui/.assets/icons/check-circle.svg
aioqui/.assets/icons/check-square.svg
aioqui/.assets/icons/check.svg
aioqui/.assets/icons/chevron-down.svg
aioqui/.assets/icons/chevron-left.svg
aioqui/.assets/icons/chevron-right.svg
aioqui/.assets/icons/chevron-up.svg
aioqui/.assets/icons/chevrons-down.svg
aioqui/.assets/icons/chevrons-left.svg
aioqui/.assets/icons/chevrons-right.svg
aioqui-2.2.2.dist-info/LICENSE.txt
aioqui-2.2.2.dist-info/METADATA
aioqui-2.2.2.dist-info/WHEEL
aioqui-2.2.2.dist-info/top_level.txt
aioqui-2.2.2.dist-info/RECORD
