Metadata-Version: 2.1
Name: aioqui
Version: 2.2.2
Summary: Asynchronous GUI framework based on PySide6
Author-email: cxllmerichie <cxllmerichie@gmail.com>
Maintainer-email: cxllmerichie <cxllmerichie@gmail.com>
License: MIT License
Project-URL: Homepage, https://github.com/cxllmerichie/aioqui
Project-URL: Bug Tracker, https://github.com/cxllmerichie/aioqui/issues
Project-URL: Repository, https://github.com/cxllmerichie/aioqui
Project-URL: Documentation, https://github.com/cxllmerichie/aioqui/README.md
Classifier: Topic :: Software Development :: Libraries :: Python Modules
Classifier: Topic :: Software Development :: User Interfaces
Classifier: Programming Language :: Python :: Implementation :: CPython
Classifier: Programming Language :: Python :: 3.10
Classifier: Environment :: X11 Applications :: Qt
Classifier: Natural Language :: English
Classifier: Development Status :: 3 - Alpha
Classifier: Intended Audience :: Developers
Classifier: Operating System :: OS Independent
Classifier: License :: OSI Approved :: MIT License
Requires-Python: >=3.10
License-File: LICENSE.txt
Requires-Dist: PySide6 (~=6.5.0)
Requires-Dist: qasync (~=0.24.0)
Requires-Dist: loguru (~=0.6.0)
